{
  "rate-1-1-1": 3.0,
  "answers-1-1-1": "1-2-3-4-5-6-7-8-9-",
  "time-1-1-1": "00:00:11.8587123",
  "rate-1-2-1": 0.0,
  "answers-1-2-1": "1-",
  "time-1-2-1": "00:00:02.7559492",
  "rate-1-3-1": 0.0,
  "answers-1-3-1": "1-",
  "time-1-3-1": "00:00:04.6676480",
  "rate-1-4-1": 5.0,
  "answers-1-4-1": "1-2-3-4-5-6-7-",
  "time-1-4-1": "00:00:14.1120262",
  "rate-1-5-1": 1.5,
  "answers-1-5-1": "1-2-3-4-5-6-7-8-9-",
  "time-1-5-1": "00:00:06.3860295",
  "rate-1-6-1": 2.5,
  "answers-1-6-1": "2-7-",
  "time-1-6-1": "00:00:02.5639745",
  "rate-1-7-1": 4.0,
  "answers-1-7-1": null,
  "time-1-7-1": "00:02:05.7678919",
  "rate-1-8-1": -7.0,
  "answers-1-8-1": "1-2-3-4-5-",
  "time-1-8-1": "00:00:08.6079055"
}